README.md
setup.cfg
setup.py
AD/__init__.py
AD/autodif.py
AD/interpreter.py
AD_testing_packaging_CS207.egg-info/PKG-INFO
AD_testing_packaging_CS207.egg-info/SOURCES.txt
AD_testing_packaging_CS207.egg-info/dependency_links.txt
AD_testing_packaging_CS207.egg-info/top_level.txt