Metadata-Version: 2.1
Name: AD-testing-packaging-CS207
Version: 0.0.0
Summary: Automatic Differentiation Package
Home-page: https://github.com/cs207-f18-WIRS/cs207-FinalProject
Author: Shenghao Jiang, Isabelle Feldhaus, Robbert Struyven, William Wang
Author-email:  
License: MIT
Keywords: Automatic differentiation,gradients,Python
Platform: UNKNOWN
Classifier: Programming Language :: Python :: 3
Classifier: License :: OSI Approved :: MIT License
